llm_groq.py
llm_groq-0.8.dist-info/LICENSE
llm_groq-0.8.dist-info/METADATA
llm_groq-0.8.dist-info/WHEEL
llm_groq-0.8.dist-info/entry_points.txt
llm_groq-0.8.dist-info/top_level.txt
llm_groq-0.8.dist-info/RECORD
