Metadata-Version: 2.2
Name: llm-groq
Version: 0.8
Author: Moritz Angermann
License: Apache-2.0
Project-URL: Homepage, https://github.com/angerman/llm-groq
Project-URL: Changelog, https://github.com/angerman/llm-groq/releases
Project-URL: Issues, https://github.com/angerman/llm-groq/issues
Project-URL: CI, https://github.com/angerman/llm-groq/actions
Classifier: License :: OSI Approved :: Apache Software License
License-File: LICENSE
Requires-Dist: llm>=0.18
Requires-Dist: groq
